mlops2024/__cli__.py
mlops2024/__click__.py
mlops2024/__init__.py
mlops2024/_version.py
mlops2024/book/_config.yml
mlops2024/book/_toc.yml
mlops2024/book/about/images/yjlee.jpeg
mlops2024/book/about/index.md
mlops2024/book/assets/assets/extra/.gitkeep
mlops2024/book/assets/extra/.gitkeep
mlops2024/book/bibs/week01.bib
mlops2024/book/index.md
mlops2024/book/projects/202021012/DUSt3R/Network_architecture.png
mlops2024/book/projects/202021012/DUSt3R/focal_length.png
mlops2024/book/projects/202021012/DUSt3R/image.png
mlops2024/book/projects/202021012/DUSt3R/index.md
mlops2024/book/projects/202021012/DUSt3R/loss_result.png
mlops2024/book/projects/202021012/DUSt3R/pose_matching.png
mlops2024/book/projects/202021012/DUSt3R/relative2.png
mlops2024/book/projects/202021012/RAG_project/index.md
mlops2024/book/projects/202021012/RAG_project/result2_ollamaembedding.png
mlops2024/book/projects/202021012/RAG_project/result_ollamaembedding.png
mlops2024/book/projects/202021012/finetuning/finetuning-vs-prompt.png
mlops2024/book/projects/202021012/finetuning/index.md
mlops2024/book/projects/202021012/index.md
mlops2024/book/projects/202121010/LectureSync/index.md
mlops2024/book/projects/202121010/LectureSync/src/rag_copy.py
mlops2024/book/projects/202121010/LectureSync/src/streamlit_frontend.py
mlops2024/book/projects/202121010/LectureSync/src/stt.py
mlops2024/book/projects/202121010/LectureSync/src/summarize_copy.py
mlops2024/book/projects/202121010/MMHuman3D/figs/10fps.png
mlops2024/book/projects/202121010/MMHuman3D/figs/1fps.png
mlops2024/book/projects/202121010/MMHuman3D/figs/8fps.png
mlops2024/book/projects/202121010/MMHuman3D/figs/after_resize_fps10.png
mlops2024/book/projects/202121010/MMHuman3D/figs/after_rtsp_fps10.png
mlops2024/book/projects/202121010/MMHuman3D/figs/bbox.png
mlops2024/book/projects/202121010/MMHuman3D/figs/deepsor_net.png
mlops2024/book/projects/202121010/MMHuman3D/figs/deepsort.png
mlops2024/book/projects/202121010/MMHuman3D/figs/default.png
mlops2024-0.6.0.dist-info/LICENSE
mlops2024-0.6.0.dist-info/METADATA
mlops2024-0.6.0.dist-info/WHEEL
mlops2024-0.6.0.dist-info/entry_points.txt
mlops2024-0.6.0.dist-info/RECORD
